postgres_wire/__init__.py
postgres_wire/constants.py
postgres_wire/fields.py
postgres_wire/pg_buffer.py
postgres_wire/pg_handler.py
postgres_wire/pg_server.py
postgres_wire-1.0.2.dist-info/METADATA
postgres_wire-1.0.2.dist-info/WHEEL
postgres_wire-1.0.2.dist-info/top_level.txt
postgres_wire-1.0.2.dist-info/RECORD
