Metadata-Version: 2.4
Name: postgres-wire
Version: 1.0.2
Summary: Add your description here
Requires-Python: >=3.13
Requires-Dist: pydantic>=2.12.5
